LICENSE
README.md
setup.py
bin/checkov
bin/checkov.cmd
checkov/__init__.py
checkov/contributor_metrics.py
checkov/logging_init.py
checkov/main.py
checkov/py.typed
checkov/runner_filter.py
checkov/version.py
checkov/ansible/__init__.py
checkov/ansible/runner.py
checkov/ansible/utils.py
checkov/ansible/checks/__init__.py
checkov/ansible/checks/base_ansible_task_check.py
checkov/ansible/checks/base_ansible_task_value_check.py
checkov/ansible/checks/registry.py
checkov/ansible/checks/graph_checks/__init__.py
checkov/ansible/checks/task/__init__.py
checkov/ansible/checks/task/aws/EC2EBSOptimized.py
checkov/ansible/checks/task/aws/EC2PublicIP.py
checkov/ansible/checks/task/aws/__init__.py
checkov/ansible/checks/task/builtin/AptAllowUnauthenticated.py
checkov/ansible/checks/task/builtin/AptForce.py
checkov/ansible/checks/task/builtin/GetUrlValidateCerts.py
checkov/ansible/checks/task/builtin/UriValidateCerts.py
checkov/ansible/checks/task/builtin/YumSslVerify.py
checkov/ansible/checks/task/builtin/YumValidateCerts.py
checkov/ansible/checks/task/builtin/__init__.py
checkov/ansible/graph_builder/__init__.py
checkov/ansible/graph_builder/local_graph.py
checkov/ansible/graph_builder/graph_components/__init__.py
checkov/ansible/graph_builder/graph_components/resource_types.py
checkov/argo_workflows/__init__.py
checkov/argo_workflows/runner.py
checkov/argo_workflows/checks/__init__.py
checkov/argo_workflows/checks/base_argo_workflows_check.py
checkov/argo_workflows/checks/registry.py
checkov/argo_workflows/checks/template/DefaultServiceAccount.py
checkov/argo_workflows/checks/template/RunAsNonRoot.py
checkov/argo_workflows/checks/template/__init__.py
checkov/argo_workflows/common/__init__.py
checkov/arm/__init__.py
checkov/arm/base_parameter_check.py
checkov/arm/base_registry.py
checkov/arm/base_resource_check.py
checkov/arm/base_resource_negative_value_check.py
checkov/arm/base_resource_value_check.py
checkov/arm/context_parser.py
checkov/arm/graph_manager.py
chekov.egg-info/PKG-INFO
chekov.egg-info/SOURCES.txt
chekov.egg-info/dependency_links.txt
chekov.egg-info/requires.txt
chekov.egg-info/top_level.txt
