Metadata-Version: 2.1
Name: chekov
Version: 2.3.273
Summary: A fake typosquat malicious library of checkov, used only for testing purposes. The library supposedly steals the user's env vars and sends it to a remote server, the domain is fake though so no data is actually stolen.
Home-page: https://github.com/bridgecrewio/checkov
Author: bridgecrew
Author-email: meet@bridgecrew.io
License: Apache License 2.0
Classifier: Environment :: Console
Classifier: Intended Audience :: Developers
Classifier: Intended Audience :: System Administrators
Classifier: License :: OSI Approved :: Apache Software License
Classifier: Programming Language :: Python :: 3 :: Only
Classifier: Programming Language :: Python :: 3.7
Classifier: Programming Language :: Python :: 3.8
Classifier: Programming Language :: Python :: 3.9
Classifier: Programming Language :: Python :: 3.10
Classifier: Programming Language :: Python :: 3.11
Classifier: Topic :: Security
Classifier: Topic :: Software Development :: Build Tools
Classifier: Typing :: Typed
Requires-Python: >=3.7
Provides-Extra: dev
License-File: LICENSE
